coreason_constitution/__init__.py
coreason_constitution/archive.py
coreason_constitution/core.py
coreason_constitution/defaults/laws.json
coreason_constitution/defaults/references.json
coreason_constitution/defaults/sentinel_rules.json
coreason_constitution/exceptions.py
coreason_constitution/interfaces.py
coreason_constitution/judge.py
coreason_constitution/main.py
coreason_constitution/revision.py
coreason_constitution/schema.py
coreason_constitution/sentinel.py
coreason_constitution/server.py
coreason_constitution/simulation.py
coreason_constitution/utils/__init__.py
coreason_constitution/utils/diff.py
coreason_constitution/utils/logger.py
coreason_economist/__init__.py
coreason_economist/models.py
coreason_economist/utils/__init__.py
coreason_economist/utils/logger.py
coreason_constitution-0.3.0.dist-info/METADATA
coreason_constitution-0.3.0.dist-info/WHEEL
coreason_constitution-0.3.0.dist-info/entry_points.txt
coreason_constitution-0.3.0.dist-info/licenses/LICENSE
coreason_constitution-0.3.0.dist-info/licenses/NOTICE
coreason_constitution-0.3.0.dist-info/RECORD
